infima_client/__init__.py
infima_client/api/__init__.py
infima_client/api/cohort_v1.py
infima_client/api/market_v0.py
infima_client/api/pool_v1.py
infima_client/api/prediction_v1.py
infima_client/api/pricing_v0.py
infima_client/api/search_v0.py
infima_client/api/utils.py
infima_client/client.py
infima_client/core/__init__.py
infima_client/core/api/__init__.py
infima_client/core/api/cohort_v1/__init__.py
infima_client/core/api/cohort_v1/cohort_v1_check_coverage.py
infima_client/core/api/cohort_v1/cohort_v1_check_exists.py
infima_client/core/api/cohort_v1/cohort_v1_find.py
infima_client/core/api/cohort_v1/cohort_v1_get_actual_prepayments.py
infima_client/core/api/cohort_v1/cohort_v1_get_cohort_summary.py
infima_client/core/api/cohort_v1/cohort_v1_get_covered_cohorts.py
infima_client/core/api/cohort_v1/cohort_v1_get_member_lists.py
infima_client/core/api/cohort_v1/cohort_v1_get_member_pools.py
infima_client/core/api/cohort_v1/cohort_v1_get_pool_memberships.py
infima_client/core/api/cohort_v1/cohort_v1_get_service_info.py
infima_client/core/api/market_v0/__init__.py
infima_client/core/api/market_v0/market_v0_get_service_info.py
infima_client/core/api/market_v0/market_v0_get_story_view.py
infima_client/core/api/market_v0/market_v0_get_view.py
infima_client/core/api/pool_v1/__init__.py
infima_client/core/api/pool_v1/pool_v1_check_coverage.py
infima_client/core/api/pool_v1/pool_v1_find.py
infima_client/core/api/pool_v1/pool_v1_get.py
infima_client/core/api/pool_v1/pool_v1_get_actual_prepayments.py
infima_client/core/api/pool_v1/pool_v1_get_all_servicers.py
infima_client/core/api/pool_v1/pool_v1_get_characteristics.py
infima_client/core/api/pool_v1/pool_v1_get_current_factor_date.py
infima_client/core/api/pool_v1/pool_v1_get_cusip_from_pool_number.py
infima_client/core/api/pool_v1/pool_v1_get_general_distributions.py
infima_client/core/api/pool_v1/pool_v1_get_geographic_distribution.py
infima_client/core/api/pool_v1/pool_v1_get_quartiles.py
infima_client-0.287.0.dist-info/WHEEL
infima_client-0.287.0.dist-info/METADATA
infima_client-0.287.0.dist-info/RECORD
