Metadata-Version: 2.1
Name: infima-client
Version: 0.287.0
Summary: A client library for accessing Infima
Author: Alex Papanicolaou
Author-email: alex@infima.io
Requires-Python: >=3.7.1,<4.0.0
Classifier: Programming Language :: Python :: 3
Classifier: Programming Language :: Python :: 3.10
Classifier: Programming Language :: Python :: 3.8
Classifier: Programming Language :: Python :: 3.9
Requires-Dist: attrs (>=20.1.0,<21.0.0)
Requires-Dist: httpx (>=0.15.4,<0.17.0)
Requires-Dist: importlib_metadata (>=4.2,<5.0); python_version >= "3.7" and python_version < "3.8"
Requires-Dist: more-itertools (>=8.12.0,<9.0.0)
Requires-Dist: pandas (>=1.1.0,<2.0.0)
Requires-Dist: python-dateutil (>=2.8.0,<3.0.0)
Requires-Dist: semver (>=2.13.0,<3.0.0)
Requires-Dist: tqdm (>=4.62.3,<5.0.0)
Requires-Dist: typing_extensions (>=4.0.1,<5.0.0); python_version >= "3.7" and python_version < "3.8"
